setup.py
zerorpc_statsd/__init__.py
zerorpc_statsd/middleware.py
zerorpc_statsd.egg-info/PKG-INFO
zerorpc_statsd.egg-info/SOURCES.txt
zerorpc_statsd.egg-info/dependency_links.txt
zerorpc_statsd.egg-info/requires.txt
zerorpc_statsd.egg-info/top_level.txt