Metadata-Version: 1.0
Name: zerorpc-statsd
Version: 0.1.0
Summary: StatsD Middleware for ZeroRPC.
Home-page: https://github.com/aluzzardi/zerorpc-statsd
Author: Andrea Luzzardi
Author-email: andrea@luzzardi.com
License: UNKNOWN
Platform: UNKNOWN
Classifier: Programming Language :: Python
Classifier: Development Status :: 4 - Beta
Classifier: Environment :: Other Environment
Classifier: Intended Audience :: Developers
Classifier: License :: OSI Approved :: MIT License
Classifier: Operating System :: OS Independent
Classifier: Topic :: Software Development :: Libraries :: Python Modules
